Workbook

Sheet Assumptions
B1: White-Label AI Infrastructure License
B2: Financial Model — Assumptions & Scenario Levers
B4: HOW TO USE THIS MODEL
B5: Blue cells are inputs — change them to run a scenario. Black cells are formulas. Do not overwrite black cells.
B6: Yellow-filled cells are the key levers to stress-test first.
B8: PRODUCT & PRICING | D8: Notes
B9: License price ($/customer/month) | C9: 1500 | D9: Per CLAUDE.md: White-Label AI Infrastructure License list price.
B11: CUSTOMER GROWTH | D11: Notes
B12: Starting customers (Month 0) | C12: 0 | D12: Model starts from zero paying licenses.
B13: New customers / month — Year 1 | C13: 2 | D13: Gross new licenses signed per month. Conservative for a single-founder cold-outreach engine.
B14: New customers / month — Year 2 | C14: 4 | D14: Assumes outreach engine + word-of-mouth roughly double the run rate.
B15: New customers / month — Year 3 | C15: 6 | D15: Continued ramp. Still modest vs. a funded sales team.
B16: Monthly logo churn | C16: 0.04 | D16: 4%/mo (~39%/yr). Realistic for early SMB SaaS; the single biggest lever on long-run size.
B18: COST STRUCTURE | D18: Notes
B19: Variable COGS ($/customer/month) | C19: 60 | D19: API/inference (Gemini), per-customer support & onboarding allocation.
B20: Fixed infrastructure ($/month) | C20: 50 | D20: Render service + Gmail relay + base tooling, independent of customer count.
B21: Payment processing (% of revenue) | C21: 0.03 | D21: Stripe blended fee.
B22: Customer acquisition cost ($/new customer) | C22: 300 | D22: Blended cost per signed license (outreach tooling, ad spend, time). Low because acquisition is automated.
B23: Fixed operating expenses ($/month) | C23: 500 | D23: Software subscriptions, misc. overhead.
B24: Founder / owner draw ($/month) | C24: 8000 | D24: Real cost of the owner's time (~$96k/yr). A model that ignores this overstates profit. Set to 0 to see pre-salary economics.
B25: Starting cash ($) | C25: 5000 | D25: Cash on hand at Month 0.
B27: VALUATION (ILLUSTRATIVE) | D27: Notes
B28: Exit multiple (EV / ending ARR) | C28: 3 | D28: Illustrative private-SaaS ARR multiple. ~39%/yr churn would compress a real multiple toward the low end. NOT a strategic-acquirer premium — see disclaimer on Summary tab.

Sheet Monthly Model
B1: Monthly Financial Model — 36 Months
B2: All figures monthly unless noted. Driven entirely by the Assumptions tab.
B4: Year | C4: Y1 | D4: Y1 | E4: Y1 | F4: Y1 | G4: Y1 | H4: Y1 | I4: Y1 | J4: Y1 | K4: Y1 | L4: Y1 | M4: Y1 | N4: Y1 | O4: Y2 | P4: Y2 | Q4: Y2 | R4: Y2 | S4: Y2 | T4: Y2 | U4: Y2 | V4: Y2 | W4: Y2 | X4: Y2 | Y4: Y2 | Z4: Y2 | AA4: Y3 | AB4: Y3 | AC4: Y3 | AD4: Y3 | AE4: Y3 | AF4: Y3 | AG4: Y3 | AH4: Y3 | AI4: Y3 | AJ4: Y3 | AK4: Y3 | AL4: Y3
B5: Month | C5: 1 | D5: 2 | E5: 3 | F5: 4 | G5: 5 | H5: 6 | I5: 7 | J5: 8 | K5: 9 | L5: 10 | M5: 11 | N5: 12 | O5: 13 | P5: 14 | Q5: 15 | R5: 16 | S5: 17 | T5: 18 | U5: 19 | V5: 20 | W5: 21 | X5: 22 | Y5: 23 | Z5: 24 | AA5: 25 | AB5: 26 | AC5: 27 | AD5: 28 | AE5: 29 | AF5: 30 | AG5: 31 | AH5: 32 | AI5: 33 | AJ5: 34 | AK5: 35 | AL5: 36
B7: CUSTOMERS
B8: Beginning customers | C8: =Assumptions!$C$12 -> 0 | D8: =C11 -> 2 | E8: =D11 -> 3.9 | F8: =E11 -> 5.7 | G8: =F11 -> 7.5 | H8: =G11 -> 9.2 | I8: =H11 -> 10.8 | J8: =I11 -> 12.4 | K8: =J11 -> 13.9 | ... AL8: =AK11 -> 86.5
B9: New customers (gross adds) | C9: =IF(C$5<=12,Assumptions!$C$13,IF(C$5<=24,Assumptions!$C$14,Assumptions!$C$15)) -> 2 | D9: =IF(D$5<=12,Assumptions!$C$13,IF(D$5<=24,Assumptions!$C$14,Assumptions!$C$15)) -> 2 | E9: =IF(E$5<=12,Assumptions!$C$13,IF(E$5<=24,Assumptions!$C$14,Assumptions!$C$15)) -> 2 | F9: =IF(F$5<=12,Assumptions!$C$13,IF(F$5<=24,Assumptions!$C$14,Assumptions!$C$15)) -> 2 | G9: =IF(G$5<=12,Assumptions!$C$13,IF(G$5<=24,Assumptions!$C$14,Assumptions!$C$15)) -> 2 | H9: =IF(H$5<=12,Assumptions!$C$13,IF(H$5<=24,Assumptions!$C$14,Assumptions!$C$15)) -> 2 | I9: =IF(I$5<=12,Assumptions!$C$13,IF(I$5<=24,Assumptions!$C$14,Assumptions!$C$15)) -> 2 | J9: =IF(J$5<=12,Assumptions!$C$13,IF(J$5<=24,Assumptions!$C$14,Assumptions!$C$15)) -> 2 | ... AL9: =IF(AL$5<=12,Assumptions!$C$13,IF(AL$5<=24,Assumptions!$C$14,Assumptions!$C$15)) -> 6
B10: Churned customers | C10: =ROUND(C8*Assumptions!$C$16,1) -> 0 | D10: =ROUND(D8*Assumptions!$C$16,1) -> 0.1 | E10: =ROUND(E8*Assumptions!$C$16,1) -> 0.2 | F10: =ROUND(F8*Assumptions!$C$16,1) -> 0.2 | G10: =ROUND(G8*Assumptions!$C$16,1) -> 0.3 | H10: =ROUND(H8*Assumptions!$C$16,1) -> 0.4 | I10: =ROUND(I8*Assumptions!$C$16,1) -> 0.4 | J10: =ROUND(J8*Assumptions!$C$16,1) -> 0.5 | ... AL10: =ROUND(AL8*Assumptions!$C$16,1) -> 3.5
B11: Ending customers | C11: =C8+C9-C10 -> 2 | D11: =D8+D9-D10 -> 3.9 | E11: =E8+E9-E10 -> 5.7 | F11: =F8+F9-F10 -> 7.5 | G11: =G8+G9-G10 -> 9.2 | H11: =H8+H9-H10 -> 10.8 | I11: =I8+I9-I10 -> 12.4 | J11: =J8+J9-J10 -> 13.9 | ... AL11: =AL8+AL9-AL10 -> 89
B13: REVENUE
B14: MRR (ending) | C14: =C11*Assumptions!$C$9 -> 3000 | D14: =D11*Assumptions!$C$9 -> 5850 | E14: =E11*Assumptions!$C$9 -> 8550 | F14: =F11*Assumptions!$C$9 -> 11250 | G14: =G11*Assumptions!$C$9 -> 13800 | H14: =H11*Assumptions!$C$9 -> 16200 | I14: =I11*Assumptions!$C$9 -> 18600 | J14: =J11*Assumptions!$C$9 -> 20850 | ... AL14: =AL11*Assumptions!$C$9 -> 133500
B15: Revenue | C15: =C14 -> 3000 | D15: =D14 -> 5850 | E15: =E14 -> 8550 | F15: =F14 -> 11250 | G15: =G14 -> 13800 | H15: =H14 -> 16200 | I15: =I14 -> 18600 | J15: =J14 -> 20850 | ... AL15: =AL14 -> 133500
B17: COST OF GOODS SOLD
B18: Variable COGS | C18: =C11*Assumptions!$C$19 -> 120 | D18: =D11*Assumptions!$C$19 -> 234 | E18: =E11*Assumptions!$C$19 -> 342 | F18: =F11*Assumptions!$C$19 -> 450 | G18: =G11*Assumptions!$C$19 -> 552 | H18: =H11*Assumptions!$C$19 -> 648 | I18: =I11*Assumptions!$C$19 -> 744 | J18: =J11*Assumptions!$C$19 -> 834 | ... AL18: =AL11*Assumptions!$C$19 -> 5340
B19: Fixed infrastructure | C19: =Assumptions!$C$20 -> 50 | D19: =Assumptions!$C$20 -> 50 | E19: =Assumptions!$C$20 -> 50 | F19: =Assumptions!$C$20 -> 50 | G19: =Assumptions!$C$20 -> 50 | H19: =Assumptions!$C$20 -> 50 | I19: =Assumptions!$C$20 -> 50 | J19: =Assumptions!$C$20 -> 50 | ... AL19: =Assumptions!$C$20 -> 50
B20: Payment processing | C20: =C15*Assumptions!$C$21 -> 90 | D20: =D15*Assumptions!$C$21 -> 175.5 | E20: =E15*Assumptions!$C$21 -> 256.5 | F20: =F15*Assumptions!$C$21 -> 337.5 | G20: =G15*Assumptions!$C$21 -> 414 | H20: =H15*Assumptions!$C$21 -> 486 | I20: =I15*Assumptions!$C$21 -> 558 | J20: =J15*Assumptions!$C$21 -> 625.5 | ... AL20: =AL15*Assumptions!$C$21 -> 4005
B21: Total COGS | C21: =SUM(C18:C20) -> 260 | D21: =SUM(D18:D20) -> 459.5 | E21: =SUM(E18:E20) -> 648.5 | F21: =SUM(F18:F20) -> 837.5 | G21: =SUM(G18:G20) -> 1016 | H21: =SUM(H18:H20) -> 1184 | I21: =SUM(I18:I20) -> 1352 | J21: =SUM(J18:J20) -> 1509.5 | ... AL21: =SUM(AL18:AL20) -> 9395
B22: Gross profit | C22: =C15-C21 -> 2740 | D22: =D15-D21 -> 5390.5 | E22: =E15-E21 -> 7901.5 | F22: =F15-F21 -> 10412.5 | G22: =G15-G21 -> 12784 | H22: =H15-H21 -> 15016 | I22: =I15-I21 -> 17248 | J22: =J15-J21 -> 19340.5 | ... AL22: =AL15-AL21 -> 124105
B23: Gross margin % | C23: =IF(C15=0,0,C22/C15) -> 0.91333333 | D23: =IF(D15=0,0,D22/D15) -> 0.92145299 | E23: =IF(E15=0,0,E22/E15) -> 0.92415205 | F23: =IF(F15=0,0,F22/F15) -> 0.92555556 | G23: =IF(G15=0,0,G22/G15) -> 0.92637681 | H23: =IF(H15=0,0,H22/H15) -> 0.92691358 | I23: =IF(I15=0,0,I22/I15) -> 0.92731183 | J23: =IF(J15=0,0,J22/J15) -> 0.92760192 | ... AL23: =IF(AL15=0,0,AL22/AL15) -> 0.92962547
B25: OPERATING EXPENSES
B26: Customer acquisition | C26: =C9*Assumptions!$C$22 -> 600 | D26: =D9*Assumptions!$C$22 -> 600 | E26: =E9*Assumptions!$C$22 -> 600 | F26: =F9*Assumptions!$C$22 -> 600 | G26: =G9*Assumptions!$C$22 -> 600 | H26: =H9*Assumptions!$C$22 -> 600 | I26: =I9*Assumptions!$C$22 -> 600 | J26: =J9*Assumptions!$C$22 -> 600 | ... AL26: =AL9*Assumptions!$C$22 -> 1800
B27: Founder / owner draw | C27: =Assumptions!$C$24 -> 8000 | D27: =Assumptions!$C$24 -> 8000 | E27: =Assumptions!$C$24 -> 8000 | F27: =Assumptions!$C$24 -> 8000 | G27: =Assumptions!$C$24 -> 8000 | H27: =Assumptions!$C$24 -> 8000 | I27: =Assumptions!$C$24 -> 8000 | J27: =Assumptions!$C$24 -> 8000 | ... AL27: =Assumptions!$C$24 -> 8000
B28: Fixed operating expenses | C28: =Assumptions!$C$23 -> 500 | D28: =Assumptions!$C$23 -> 500 | E28: =Assumptions!$C$23 -> 500 | F28: =Assumptions!$C$23 -> 500 | G28: =Assumptions!$C$23 -> 500 | H28: =Assumptions!$C$23 -> 500 | I28: =Assumptions!$C$23 -> 500 | J28: =Assumptions!$C$23 -> 500 | ... AL28: =Assumptions!$C$23 -> 500
B29: Total OpEx | C29: =SUM(C26:C28) -> 9100 | D29: =SUM(D26:D28) -> 9100 | E29: =SUM(E26:E28) -> 9100 | F29: =SUM(F26:F28) -> 9100 | G29: =SUM(G26:G28) -> 9100 | H29: =SUM(H26:H28) -> 9100 | I29: =SUM(I26:I28) -> 9100 | J29: =SUM(J26:J28) -> 9100 | ... AL29: =SUM(AL26:AL28) -> 10300
B31: PROFITABILITY & CASH
B32: EBITDA | C32: =C22-C29 -> -6360 | D32: =D22-D29 -> -3709.5 | E32: =E22-E29 -> -1198.5 | F32: =F22-F29 -> 1312.5 | G32: =G22-G29 -> 3684 | H32: =H22-H29 -> 5916 | I32: =I22-I29 -> 8148 | J32: =J22-J29 -> 10240.5 | ... AL32: =AL22-AL29 -> 113805
B33: EBITDA margin % | C33: =IF(C15=0,0,C32/C15) -> -2.12 | D33: =IF(D15=0,0,D32/D15) -> -0.63410256 | E33: =IF(E15=0,0,E32/E15) -> -0.14017544 | F33: =IF(F15=0,0,F32/F15) -> 0.11666667 | G33: =IF(G15=0,0,G32/G15) -> 0.26695652 | H33: =IF(H15=0,0,H32/H15) -> 0.36518519 | I33: =IF(I15=0,0,I32/I15) -> 0.43806452 | J33: =IF(J15=0,0,J32/J15) -> 0.49115108 | ... AL33: =IF(AL15=0,0,AL32/AL15) -> 0.85247191
B34: Beginning cash | C34: =Assumptions!$C$25 -> 5000 | D34: =C35 -> -1360 | E34: =D35 -> -5069.5 | F34: =E35 -> -6268 | G34: =F35 -> -4955.5 | H34: =G35 -> -1271.5 | I34: =H35 -> 4644.5 | J34: =I35 -> 12792.5 | K34: =J35 -> 23033 | ... AL34: =AK35 -> 1575779
B35: Ending cash | C35: =C34+C32 -> -1360 | D35: =D34+D32 -> -5069.5 | E35: =E34+E32 -> -6268 | F35: =F34+F32 -> -4955.5 | G35: =G34+G32 -> -1271.5 | H35: =H34+H32 -> 4644.5 | I35: =I34+I32 -> 12792.5 | J35: =J34+J32 -> 23033 | ... AL35: =AL34+AL32 -> 1689584

Sheet Annual Summary
B1: Annual Summary & Illustrative Valuation
B2: Rolled up from the Monthly Model tab.
B4: ($ per year unless noted) | C4: Year 1 | D4: Year 2 | E4: Year 3
B6: CUSTOMERS
B7: New customers signed | C7: =SUM('Monthly Model'!C9:N9) -> 24 | D7: =SUM('Monthly Model'!O9:Z9) -> 48 | E7: =SUM('Monthly Model'!AA9:AL9) -> 72
B8: Ending customers | C8: ='Monthly Model'!N11 -> 19.3 | D8: ='Monthly Model'!Z11 -> 50.5 | E8: ='Monthly Model'!AL11 -> 89
B9: Ending ARR | C9: ='Monthly Model'!N11*Assumptions!$C$9*12 -> 347400 | D9: ='Monthly Model'!Z11*Assumptions!$C$9*12 -> 909000 | E9: ='Monthly Model'!AL11*Assumptions!$C$9*12 -> 1602000
B11: P&L
B12: Revenue | C12: =SUM('Monthly Model'!C15:N15) -> 202050 | D12: =SUM('Monthly Model'!O15:Z15) -> 673950 | E12: =SUM('Monthly Model'!AA15:AL15) -> 1312800
B13: Gross profit | C13: =SUM('Monthly Model'!C22:N22) -> 187306.5 | D13: =SUM('Monthly Model'!O22:Z22) -> 626173.5 | E13: =SUM('Monthly Model'!AA22:AL22) -> 1220304
B14: Gross margin % | C14: =IF(C12=0,0,C13/C12) -> 0.92703044 | D14: =IF(D12=0,0,D13/D12) -> 0.92910973 | E14: =IF(E12=0,0,E13/E12) -> 0.92954296
B15: EBITDA | C15: =SUM('Monthly Model'!C32:N32) -> 78106.5 | D15: =SUM('Monthly Model'!O32:Z32) -> 509773.5 | E15: =SUM('Monthly Model'!AA32:AL32) -> 1096704
B16: EBITDA margin % | C16: =IF(C12=0,0,C15/C12) -> 0.38657016 | D16: =IF(D12=0,0,D15/D12) -> 0.75639662 | E16: =IF(E12=0,0,E15/E12) -> 0.83539305
B17: Ending cash | C17: ='Monthly Model'!N35 -> 83106.5 | D17: ='Monthly Model'!Z35 -> 592880 | E17: ='Monthly Model'!AL35 -> 1689584
B19: ILLUSTRATIVE VALUATION (YEAR 3)
B20: Ending ARR (Year 3) | C20: =E9 -> 1602000
B21: Exit multiple (EV / ARR) | C21: =Assumptions!$C$28 -> 3
B22: Implied enterprise value | C22: =C20*C21 -> 4806000
B24: DISCLAIMER
B25: This valuation is illustrative only. It multiplies modeled Year-3 ARR by a generic private-SaaS revenue multiple (an input you can change on the Assumptions tab). It is NOT an offer, and it is NOT a strategic-acquirer / 'sell to Apple' outcome — the README's big-corp exit scenario is not supported by any of these numbers. At this scale the realistic buyer is another operator or a small PE roll-up, and the ~39%/yr logo churn assumed here would pull a real multiple toward the low end of the range. Treat the implied value as a directional sanity check on the business you are actually building, not a price tag.
